pktools/__init__.py
pktools/daemon.py
pktools/generic.py
pktools/notifiers.py
pktools-0.2.2.dist-info/LICENSE
pktools-0.2.2.dist-info/WHEEL
pktools-0.2.2.dist-info/METADATA
pktools-0.2.2.dist-info/RECORD
