Metadata-Version: 2.1
Name: pktools
Version: 0.2.2
Summary: 
Author: katmai
Author-email: katmai.mobil@gmail.com
Requires-Python: >=3.7,<4.0
Classifier: Programming Language :: Python :: 3
Classifier: Programming Language :: Python :: 3.7
Classifier: Programming Language :: Python :: 3.8
Classifier: Programming Language :: Python :: 3.9
Requires-Dist: ccxt (>=1.38.50,<2.0.0)
Requires-Dist: requests (>=2.25.0,<3.0.0)
Requires-Dist: toml (>=0.10.2,<0.11.0)
